MANIFEST.in
README.md
setup.cfg
setup.py
tests/__init__.py
tests/test_twipper.py
twipper/__init__.py
twipper/batch.py
twipper/credentials.py
twipper/premium.py
twipper/streaming.py
twipper/utils.py
twipper.egg-info/PKG-INFO
twipper.egg-info/SOURCES.txt
twipper.egg-info/dependency_links.txt
twipper.egg-info/requires.txt
twipper.egg-info/top_level.txt