Metadata-Version: 2.1
Name: twipper
Version: 0.1.3
Summary: twipper - is a Twitter API wrapper for both free and premium plans developed on Python
Home-page: https://github.com/alvarob96/twipper
Author: Alvaro Bartolome
Author-email: alvarob96@usal.es
License: GNU General Public License v3 (GPLv3)
Download-URL: https://github.com/alvarob96/twipper/archive/0.1.3.tar.gz
Project-URL: Bug Reports, https://github.com/alvarob96/twipper/issues
Project-URL: Source, https://github.com/alvarob96/twipper
Project-URL: Documentation, https://twipper.readthedocs.io/
Keywords: twitter,wrapper,api
Platform: UNKNOWN
Classifier: Development Status :: 3 - Alpha
Classifier: Programming Language :: Python :: 3 :: Only
Classifier: Programming Language :: Python :: 3.5
Classifier: Programming Language :: Python :: 3.6
Classifier: Programming Language :: Python :: 3.7
Classifier: License :: OSI Approved :: GNU General Public License v3 (GPLv3)
Classifier: Intended Audience :: Developers
Classifier: Topic :: Scientific/Engineering :: Information Analysis
Classifier: Topic :: Software Development :: Libraries
Requires-Python: >=3
